setup.py
JFB/__init__.py
JFB/utils.py
JFB.egg-info/PKG-INFO
JFB.egg-info/SOURCES.txt
JFB.egg-info/dependency_links.txt
JFB.egg-info/top_level.txt