Metadata-Version: 1.0
Name: JFB
Version: 21.4.7.2
Summary: 一些utils方法
Home-page: https://github.com/jiangfubang/jfb
Author: JiangFubang
Author-email: luckybang@163.com
License: MIT Licence
Keywords: pip,utils,JFB
Platform: any
